oklo/__init__.py
oklo/core/__init__.py
oklo/core/data.py
oklo/core/defs.py
oklo/core/elements.py
oklo/core/factory.py
oklo/core/ids.py
oklo/core/model.py
oklo/core/network.py
oklo/core/nuclide.py
oklo/core/reaction.py
oklo/core/units.py
oklo/data/isomers_nndc.py
oklo/data/mass.mas12
oklo/data/endfb_vii/nfpy_9228_92-U-235.dat
oklo/data/endfb_vii/nfpy_9237_92-U-238.dat
oklo/data/endfb_vii/nfpy_9437_94-Pu-239.dat
oklo/data/endfb_vii/nfpy_9443_94-Pu-241.dat
oklo/data/ensdf/beta_decays_ensdf6_ahayes.txt
oklo/models/__init__.py
oklo/models/betaspectrum.py
oklo/models/fissionyield.py
oklo/models/masseval.py
oklo/tests/__init__.py
oklo/tests/test_ids.py
oklo/tests/test_nuclide.py
oklo/tests/test_reaction.py
oklo/utils/__init__.py
oklo/utils/betadecay.py
oklo/utils/parsers.py
oklo-0.1.dist-info/DESCRIPTION.rst
oklo-0.1.dist-info/METADATA
oklo-0.1.dist-info/metadata.json
oklo-0.1.dist-info/RECORD
oklo-0.1.dist-info/top_level.txt
oklo-0.1.dist-info/WHEEL
