Metadata-Version: 2.0
Name: oklo
Version: 0.1
Summary: A toolkit for modeling nuclides and nuclear reactions.
Home-page: https://github.com/dadwyer/oklo
Author: Dr. Dan Dwyer
Author-email: dadwyer@lbl.gov
License: GPL
Keywords: physics nuclear reactor beta decay neutrino
Platform: UNKNOWN
Classifier: Development Status :: 3 - Alpha
Classifier: Intended Audience :: Science/Research
Classifier: Topic :: Scientific/Engineering :: Physics
Classifier: License :: OSI Approved :: GNU General Public License (GPL)
Classifier: Programming Language :: Python :: 2
Classifier: Programming Language :: Python :: 2.6
Classifier: Programming Language :: Python :: 2.7
Classifier: Programming Language :: Python :: 3
Classifier: Programming Language :: Python :: 3.2
Classifier: Programming Language :: Python :: 3.3
Classifier: Programming Language :: Python :: 3.4
Requires-Dist: numpy
